{"title":{"number":"1170876","type":"Повідомлення про повернення","code":"011","date":"2019-01-03","order_number":"4000000001","doc_basis":[{"number":"000000217","type":"Видаткова накладна","code":"006","date":"2019-01-01"}]},"parties":{"partners":[{"status":"Покупець","type":"Юридична","name":"ТОВАРИСТВО З ОБМЕЖЕНОЮ ВІДПОВІДАЛЬНІСТЮ \"ТОВ\"","code":"31111149","inn":"121212121212","spdv":"111111111","gln":"1111111111112"},{"status":"Продавець","type":"Юридична","name":"ТОВАРИСТВО З ОБМЕЖЕНОЮ ВIДПОВIДАЛЬНIСТЮ \"ТЕСТ\"","code":"11111111","inn":"222222222222","spdv":"1234567890121","gln":"1414141414141"}]},"parameters":{"parameter":[{"id":"1","name":"Номер податкової накладної"},{"id":"2","name":"Дата податкової накладної"},{"id":"3","name":"Тара","text":"Ні"},{"id":"4","name":"Місце складання","text":"м.Київ, Тестова вул. 1"}]},"table":{"position":[{"position_number":"1","barcode":[{"id":"1","value":"4820153870482"}],"articul_buyer":"291085","description":"Хліб Пушкарівський нарізний 600г в плівці Кулиничі","unit":"шт.","price_base":12.4,"vat":2.48,"price":14.88,"total":{"sum_without_vat":62.0,"sum_vat":12.4,"sum":74.4},"returns":{"qty":5.0},"id":"1"}]},"total":{"sum_without_vat":677.15,"vat":135.43,"sum":812.58}}